Metadata-Version: 2.1
Name: eth-utils-qtum
Version: 1.9.5.1
Summary: Common utility functions for ethereum codebases.
Home-page: https://github.com/qtumproject/eth-utils
Author: Piper Merriam
Author-email: pipermerriam@gmail.com
License: MIT
Keywords: ethereum
Platform: UNKNOWN
Classifier: Intended Audience :: Developers
Classifier: License :: OSI Approved :: MIT License
Classifier: Natural Language :: English
Classifier: Programming Language :: Python :: 3
Classifier: Programming Language :: Python :: 3.5
Classifier: Programming Language :: Python :: 3.6
Classifier: Programming Language :: Python :: 3.7
Classifier: Programming Language :: Python :: 3.8
Classifier: Programming Language :: Python :: Implementation :: PyPy
Requires-Python: >=3.5,!=3.5.2,<4
Requires-Dist: eth-hash-qtum (<1.0.0,>=0.1.0)
Requires-Dist: eth-typing (<3.0.0,>=2.2.1)
Requires-Dist: toolz (<1,>0.8.2) ; implementation_name == "pypy"
Provides-Extra: deploy
Requires-Dist: bumpversion (<1.0.0,>=0.5.3) ; extra == 'deploy'
Requires-Dist: tox (<3.0.0,>=2.9.1) ; extra == 'deploy'
Requires-Dist: wheel (<1.0.0,>=0.30.0) ; extra == 'deploy'
Provides-Extra: dev
Requires-Dist: twine (<2,>=1.13) ; extra == 'dev'
Requires-Dist: Sphinx (<2,>=1.5.5) ; extra == 'dev'
Requires-Dist: sphinx-rtd-theme (<2,>=0.1.9) ; extra == 'dev'
Requires-Dist: towncrier (<20,>=19.2.0) ; extra == 'dev'
Requires-Dist: black (<19,>=18.6b4) ; extra == 'dev'
Requires-Dist: flake8 (<4.0.0,>=3.7.0) ; extra == 'dev'
Requires-Dist: isort (==4.3.18) ; extra == 'dev'
Requires-Dist: mypy (==0.720) ; extra == 'dev'
Requires-Dist: pytest (<4.0.0,>=3.4.1) ; extra == 'dev'
Requires-Dist: hypothesis (<5.0.0,>=4.43.0) ; extra == 'dev'
Requires-Dist: pytest-pythonpath (<1.0,>=0.3) ; extra == 'dev'
Requires-Dist: bumpversion (<1.0.0,>=0.5.3) ; extra == 'dev'
Requires-Dist: tox (<3.0.0,>=2.9.1) ; extra == 'dev'
Requires-Dist: wheel (<1.0.0,>=0.30.0) ; extra == 'dev'
Provides-Extra: doc
Requires-Dist: Sphinx (<2,>=1.5.5) ; extra == 'doc'
Requires-Dist: sphinx-rtd-theme (<2,>=0.1.9) ; extra == 'doc'
Requires-Dist: towncrier (<20,>=19.2.0) ; extra == 'doc'
Provides-Extra: lint
Requires-Dist: black (<19,>=18.6b4) ; extra == 'lint'
Requires-Dist: flake8 (<4.0.0,>=3.7.0) ; extra == 'lint'
Requires-Dist: isort (==4.3.18) ; extra == 'lint'
Requires-Dist: mypy (==0.720) ; extra == 'lint'
Requires-Dist: pytest (<4.0.0,>=3.4.1) ; extra == 'lint'
Provides-Extra: test
Requires-Dist: hypothesis (<5.0.0,>=4.43.0) ; extra == 'test'
Requires-Dist: pytest (<4.0.0,>=3.4.1) ; extra == 'test'
Requires-Dist: pytest-pythonpath (<1.0,>=0.3) ; extra == 'test'
